languageIdentiPackage/__init__.py
languageIdentiPackage/xiaoTangTest.py
languageIdentiPackage-0.0.2.dist-info/METADATA
languageIdentiPackage-0.0.2.dist-info/WHEEL
languageIdentiPackage-0.0.2.dist-info/top_level.txt
languageIdentiPackage-0.0.2.dist-info/RECORD
