Metadata-Version: 2.1
Name: languageIdentiPackage
Version: 0.0.2
Summary: Image kernel.
Home-page: https://github.com/taw19960426/languageIdentiPackage.git
Author: ken
Author-email: kenbliky@gmail.com
License: UNKNOWN
Platform: UNKNOWN
Classifier: Programming Language :: Python :: 3
Classifier: License :: OSI Approved :: MIT License
Classifier: Operating System :: OS Independent
Requires-Python: >=3.6
